avatargen/__init__.py
avatargen/generation.py
avatargen_fiflyc-0.0.6.dist-info/LICENSE
avatargen_fiflyc-0.0.6.dist-info/METADATA
avatargen_fiflyc-0.0.6.dist-info/WHEEL
avatargen_fiflyc-0.0.6.dist-info/top_level.txt
avatargen_fiflyc-0.0.6.dist-info/RECORD
