Metadata-Version: 2.1
Name: avatargen-fiflyc
Version: 0.0.6
Summary: A GitHub-esque avatar image generator written in Python.
Home-page: https://github.com/innix/github-avatar-generator
Author: FiFlyC
Author-email: combolev@gmail.com
License: MIT
Platform: UNKNOWN
Classifier: Programming Language :: Python :: 3
Classifier: Programming Language :: Python :: 3.6
Classifier: License :: OSI Approved :: MIT License
Classifier: Operating System :: OS Independent
Requires-Python: >=3.6
License-File: LICENSE
Requires-Dist: Pillow
